{
	"configurations" : 
	[
		{
			"directories" : 
			[
				{
					"build" : ".",
					"hasInstallRule" : true,
					"jsonFile" : "directory-.-ce4ab760200885e14866.json",
					"minimumCMakeVersion" : 
					{
						"string" : "3.12"
					},
					"projectIndex" : 0,
					"source" : ".",
					"targetIndexes" : 
					[
						0,
						1,
						2,
						3,
						4,
						5
					]
				}
			],
			"name" : "",
			"projects" : 
			[
				{
					"directoryIndexes" : 
					[
						0
					],
					"name" : "examples_rclcpp_minimal_composition",
					"targetIndexes" : 
					[
						0,
						1,
						2,
						3,
						4,
						5
					]
				}
			],
			"targets" : 
			[
				{
					"directoryIndex" : 0,
					"id" : "composition_composed::@6890427a1f51a3e7e1df",
					"jsonFile" : "target-composition_composed-f3af1f8873bab8450381.json",
					"name" : "composition_composed",
					"projectIndex" : 0
				},
				{
					"directoryIndex" : 0,
					"id" : "composition_nodes::@6890427a1f51a3e7e1df",
					"jsonFile" : "target-composition_nodes-b327f79d30cc5a753459.json",
					"name" : "composition_nodes",
					"projectIndex" : 0
				},
				{
					"directoryIndex" : 0,
					"id" : "composition_publisher::@6890427a1f51a3e7e1df",
					"jsonFile" : "target-composition_publisher-c195aace2186fc195fb9.json",
					"name" : "composition_publisher",
					"projectIndex" : 0
				},
				{
					"directoryIndex" : 0,
					"id" : "composition_subscriber::@6890427a1f51a3e7e1df",
					"jsonFile" : "target-composition_subscriber-a1716166abc0a4cabb0f.json",
					"name" : "composition_subscriber",
					"projectIndex" : 0
				},
				{
					"directoryIndex" : 0,
					"id" : "examples_rclcpp_minimal_composition_uninstall::@6890427a1f51a3e7e1df",
					"jsonFile" : "target-examples_rclcpp_minimal_composition_uninstall-730a80cb3c98de337361.json",
					"name" : "examples_rclcpp_minimal_composition_uninstall",
					"projectIndex" : 0
				},
				{
					"directoryIndex" : 0,
					"id" : "uninstall::@6890427a1f51a3e7e1df",
					"jsonFile" : "target-uninstall-9c4fb2e769d9675a39f2.json",
					"name" : "uninstall",
					"projectIndex" : 0
				}
			]
		}
	],
	"kind" : "codemodel",
	"paths" : 
	{
		"build" : "/home/diego/Documents/diego_labiras/ros_ws/build/examples_rclcpp_minimal_composition",
		"source" : "/home/diego/Documents/diego_labiras/ros_ws/src/examples/rclcpp/composition/minimal_composition"
	},
	"version" : 
	{
		"major" : 2,
		"minor" : 3
	}
}
